{"cameraMode":{"drawMode":0,"name":"Shaded","section":"Shading Mode"},"sceneLighting":false,"audioPlay":false,"sceneViewState":{"showFog":true,"showMaterialUpdate":false,"showSkybox":false,"showFlares":true,"showImageEffects":true,"showParticleSystems":true},"in2DMode":false,"pivot":{"x":-0.4480454921722412,"y":-0.6868829131126404,"z":0.005704283714294434},"rotation":{"x":-0.11877759546041489,"y":-0.49977725744247439,"z":0.0693957582116127,"w":-0.8551735877990723},"size":2.3411223888397219,"orthographic":false}